databricks_langchain/__init__.py
databricks_langchain/chat_models.py
databricks_langchain/checkpoint.py
databricks_langchain/embeddings.py
databricks_langchain/genie.py
databricks_langchain/multi_server_mcp_client.py
databricks_langchain/store.py
databricks_langchain/utils.py
databricks_langchain/vector_search_retriever_tool.py
databricks_langchain/vectorstores.py
databricks_langchain/uc_ai/__init__.py
databricks_langchain-0.12.1.dist-info/METADATA
databricks_langchain-0.12.1.dist-info/WHEEL
databricks_langchain-0.12.1.dist-info/RECORD
