Metadata-Version: 2.4
Name: databricks-langchain
Version: 0.12.1
Summary: Support for Databricks AI support in LangChain
Author-email: Databricks <agent-feedback@databricks.com>
License: Apache-2.0
Requires-Python: >=3.10
Requires-Dist: databricks-ai-bridge>=0.4.2
Requires-Dist: databricks-mcp>=0.5.1
Requires-Dist: databricks-sdk>=0.65.0
Requires-Dist: databricks-vectorsearch>=0.50
Requires-Dist: langchain-mcp-adapters>=0.1.13
Requires-Dist: langchain>=1.0.0
Requires-Dist: mlflow>=2.20.1
Requires-Dist: openai>=1.99.9
Requires-Dist: pydantic>2.10.0
Requires-Dist: unitycatalog-langchain[databricks]>=0.3.0
Provides-Extra: dev
Requires-Dist: pytest; extra == 'dev'
Requires-Dist: pytest-asyncio; extra == 'dev'
Requires-Dist: ruff==0.6.4; extra == 'dev'
Requires-Dist: typing-extensions; extra == 'dev'
Provides-Extra: integration
Requires-Dist: anyio; extra == 'integration'
Requires-Dist: langgraph>=0.2.27; extra == 'integration'
Requires-Dist: pytest-asyncio; extra == 'integration'
Requires-Dist: pytest-timeout>=2.3.1; extra == 'integration'
Provides-Extra: memory
Requires-Dist: databricks-ai-bridge[memory]>=0.10.0; extra == 'memory'
Requires-Dist: langgraph-checkpoint-postgres>=2.0.0; extra == 'memory'
